{"frames":{"blast_flow_00024.png":{"frame":{"x":1521,"y":856,"w":73,"h":147},"rotated":true,"trimmed":true,"spriteSourceSize":{"x":7,"y":0,"w":73,"h":147},"sourceSize":{"w":86,"h":156}},"blast_flow_00025.png":{"frame":{"x":1471,"y":779,"w":75,"h":147},"rotated":true,"trimmed":true,"spriteSourceSize":{"x":5,"y":0,"w":75,"h":147},"sourceSize":{"w":86,"h":156}},"blast_flow_00026.png":{"frame":{"x":1657,"y":598,"w":75,"h":147},"rotated":false,"trimmed":true,"spriteSourceSize":{"x":5,"y":0,"w":75,"h":147},"sourceSize":{"w":86,"h":156}},"blast_flow_00027.png":{"frame":{"x":1520,"y":450,"w":77,"h":146},"rotated":true,"trimmed":true,"spriteSourceSize":{"x":4,"y":0,"w":77,"h":146},"sourceSize":{"w":86,"h":156}},"blast_flow_00028.png":{"frame":{"x":1668,"y":450,"w":77,"h":146},"rotated":false,"trimmed":true,"spriteSourceSize":{"x":4,"y":0,"w":77,"h":146},"sourceSize":{"w":86,"h":156}},"blast_flow_00029.png":{"frame":{"x":1797,"y":657,"w":72,"h":147},"rotated":false,"trimmed":true,"spriteSourceSize":{"x":10,"y":0,"w":72,"h":147},"sourceSize":{"w":86,"h":156}},"blast_flow_00030.png":{"frame":{"x":1792,"y":446,"w":77,"h":148},"rotated":false,"trimmed":true,"spriteSourceSize":{"x":6,"y":0,"w":77,"h":148},"sourceSize":{"w":86,"h":156}},"blast_flow_00031.png":{"frame":{"x":1792,"y":150,"w":78,"h":146},"rotated":false,"trimmed":true,"spriteSourceSize":{"x":5,"y":0,"w":78,"h":146},"sourceSize":{"w":86,"h":156}},"blast_flow_00032.png":{"frame":{"x":1792,"y":1,"w":80,"h":147},"rotated":false,"trimmed":true,"spriteSourceSize":{"x":4,"y":0,"w":80,"h":147},"sourceSize":{"w":86,"h":156}},"blast_flow_00033.png":{"frame":{"x":1372,"y":450,"w":81,"h":146},"rotated":true,"trimmed":true,"spriteSourceSize":{"x":3,"y":0,"w":81,"h":146},"sourceSize":{"w":86,"h":156}},"blast_flow_00034.png":{"frame":{"x":1372,"y":860,"w":82,"h":147},"rotated":true,"trimmed":true,"spriteSourceSize":{"x":2,"y":0,"w":82,"h":147},"sourceSize":{"w":86,"h":156}},"blast_flow_00035.png":{"frame":{"x":1792,"y":298,"w":78,"h":146},"rotated":false,"trimmed":true,"spriteSourceSize":{"x":2,"y":0,"w":78,"h":146},"sourceSize":{"w":86,"h":156}},"energy_seq_00048.png":{"frame":{"x":1732,"y":891,"w":62,"h":56},"rotated":false,"trimmed":true,"spriteSourceSize":{"x":14,"y":6,"w":62,"h":56},"sourceSize":{"w":82,"h":73}},"energy_seq_00049.png":{"frame":{"x":1801,"y":806,"w":62,"h":59},"rotated":false,"trimmed":true,"spriteSourceSize":{"x":13,"y":5,"w":62,"h":59},"sourceSize":{"w":82,"h":73}},"energy_seq_00050.png":{"frame":{"x":1801,"y":867,"w":62,"h":59},"rotated":false,"trimmed":true,"spriteSourceSize":{"x":12,"y":5,"w":62,"h":59},"sourceSize":{"w":82,"h":73}},"energy_seq_00051.png":{"frame":{"x":1523,"y":529,"w":65,"h":59},"rotated":true,"trimmed":true,"spriteSourceSize":{"x":12,"y":5,"w":65,"h":59},"sourceSize":{"w":82,"h":73}},"energy_seq_00052.png":{"frame":{"x":1776,"y":596,"w":73,"h":59},"rotated":false,"trimmed":true,"spriteSourceSize":{"x":4,"y":5,"w":73,"h":59},"sourceSize":{"w":82,"h":73}},"energy_seq_00053.png":{"frame":{"x":1682,"y":747,"w":73,"h":58},"rotated":true,"trimmed":true,"spriteSourceSize":{"x":4,"y":6,"w":73,"h":58},"sourceSize":{"w":82,"h":73}},"energy_seq_00054.png":{"frame":{"x":1372,"y":533,"w":74,"h":61},"rotated":false,"trimmed":true,"spriteSourceSize":{"x":4,"y":6,"w":74,"h":61},"sourceSize":{"w":82,"h":73}},"energy_seq_00055.png":{"frame":{"x":1620,"y":779,"w":73,"h":60},"rotated":true,"trimmed":true,"spriteSourceSize":{"x":5,"y":7,"w":73,"h":60},"sourceSize":{"w":82,"h":73}},"energy_seq_00056.png":{"frame":{"x":1670,"y":854,"w":73,"h":60},"rotated":true,"trimmed":true,"spriteSourceSize":{"x":5,"y":7,"w":73,"h":60},"sourceSize":{"w":82,"h":73}},"energy_seq_00057.png":{"frame":{"x":1448,"y":533,"w":73,"h":61},"rotated":false,"trimmed":true,"spriteSourceSize":{"x":5,"y":6,"w":73,"h":61},"sourceSize":{"w":82,"h":73}},"energy_seq_00058.png":{"frame":{"x":1584,"y":529,"w":71,"h":62},"rotated":false,"trimmed":true,"spriteSourceSize":{"x":6,"y":6,"w":71,"h":62},"sourceSize":{"w":82,"h":73}},"energy_seq_00059.png":{"frame":{"x":1734,"y":657,"w":70,"h":61},"rotated":true,"trimmed":true,"spriteSourceSize":{"x":7,"y":6,"w":70,"h":61},"sourceSize":{"w":82,"h":73}},"laser_beam.png":{"frame":{"x":1747,"y":450,"w":27,"h":180},"rotated":false,"trimmed":true,"spriteSourceSize":{"x":4,"y":4,"w":27,"h":180},"sourceSize":{"w":34,"h":186}},"laser_blast.png":{"frame":{"x":1471,"y":596,"w":181,"h":184},"rotated":true,"trimmed":true,"spriteSourceSize":{"x":3,"y":4,"w":181,"h":184},"sourceSize":{"w":187,"h":192}},"laser_blast_back_00024.png":{"frame":{"x":1,"y":1,"w":482,"h":445},"rotated":true,"trimmed":true,"spriteSourceSize":{"x":25,"y":10,"w":482,"h":445},"sourceSize":{"w":514,"h":466}},"laser_blast_back_00025.png":{"frame":{"x":448,"y":1,"w":478,"h":450},"rotated":true,"trimmed":true,"spriteSourceSize":{"x":27,"y":9,"w":478,"h":450},"sourceSize":{"w":514,"h":466}},"laser_blast_back_00026.png":{"frame":{"x":446,"y":485,"w":472,"h":455},"rotated":false,"trimmed":true,"spriteSourceSize":{"x":32,"y":8,"w":472,"h":455},"sourceSize":{"w":514,"h":466}},"laser_blast_back_00027.png":{"frame":{"x":900,"y":1,"w":471,"h":455},"rotated":true,"trimmed":true,"spriteSourceSize":{"x":25,"y":9,"w":471,"h":455},"sourceSize":{"w":514,"h":466}},"laser_blast_back_00028.png":{"frame":{"x":1,"y":485,"w":460,"h":443},"rotated":true,"trimmed":true,"spriteSourceSize":{"x":16,"y":15,"w":460,"h":443},"sourceSize":{"w":514,"h":466}},"laser_blast_back_00029.png":{"frame":{"x":1357,"y":1,"w":447,"h":433},"rotated":true,"trimmed":true,"spriteSourceSize":{"x":18,"y":23,"w":447,"h":433},"sourceSize":{"w":514,"h":466}},"laser_blast_back_00030.png":{"frame":{"x":1732,"y":822,"w":67,"h":67},"rotated":false,"trimmed":true,"spriteSourceSize":{"x":3,"y":3,"w":67,"h":67},"sourceSize":{"w":77,"h":70}},"laser_blast_back_00031.png":{"frame":{"x":920,"y":474,"w":450,"h":454},"rotated":false,"trimmed":true,"spriteSourceSize":{"x":18,"y":12,"w":450,"h":454},"sourceSize":{"w":514,"h":466}},"laser_pointer.png":{"frame":{"x":1372,"y":596,"w":97,"h":262},"rotated":false,"trimmed":true,"spriteSourceSize":{"x":10,"y":0,"w":97,"h":262},"sourceSize":{"w":116,"h":275}}},"meta":{"app":"http://www.codeandweb.com/texturepacker","version":"1.0","image":"atlas0-xhdpi.png","format":"RGBA8888","size":{"w":1873,"h":948},"scale":"1","smartupdate":"$TexturePacker:SmartUpdate:ed5de866ec7327a8490fb4611823ab40:baf2f279851e0129f7e56d94b9e66ce2:e171a174da30094a3ba2a000ede4bfd6$"}}