[{"__type__":"cc.SpriteFrame","content":{"name":"bTaixiu3","texture":"81CTz4G2ZM065GDhXT/xVq","rect":[0,0,117,94],"offset":[-0.5,0.5],"originalSize":[118,95]}},{"__type__":"cc.BitmapFont","_name":"bTaixiu3","spriteFrame":{"__uuid__":"23ptdhi5tH6KZfL79/mjP0"},"fontSize":55,"_fntConfig":{"commonHeight":32,"fontSize":55,"atlasName":"bTaixiu3.png","fontDefDictionary":{"9":{"rect":{"x":0,"y":0,"width":0,"height":0},"xOffset":0,"yOffset":0,"xAdvance":80},"32":{"rect":{"x":0,"y":0,"width":0,"height":0},"xOffset":0,"yOffset":0,"xAdvance":10},"48":{"rect":{"x":0,"y":60,"width":26,"height":31},"xOffset":0,"yOffset":2,"xAdvance":25},"49":{"rect":{"x":101,"y":62,"width":16,"height":29},"xOffset":0,"yOffset":3,"xAdvance":15},"50":{"rect":{"x":78,"y":64,"width":22,"height":30},"xOffset":0,"yOffset":2,"xAdvance":21},"51":{"rect":{"x":83,"y":0,"width":21,"height":31},"xOffset":0,"yOffset":2,"xAdvance":20},"52":{"rect":{"x":53,"y":64,"width":24,"height":29},"xOffset":0,"yOffset":3,"xAdvance":23},"53":{"rect":{"x":59,"y":0,"width":23,"height":31},"xOffset":0,"yOffset":2,"xAdvance":22},"54":{"rect":{"x":53,"y":32,"width":25,"height":31},"xOffset":0,"yOffset":2,"xAdvance":24},"55":{"rect":{"x":79,"y":32,"width":22,"height":29},"xOffset":0,"yOffset":3,"xAdvance":21},"56":{"rect":{"x":27,"y":60,"width":25,"height":31},"xOffset":0,"yOffset":2,"xAdvance":24},"57":{"rect":{"x":33,"y":0,"width":25,"height":31},"xOffset":0,"yOffset":2,"xAdvance":24},"75":{"rect":{"x":0,"y":30,"width":27,"height":29},"xOffset":0,"yOffset":3,"xAdvance":26},"77":{"rect":{"x":0,"y":0,"width":32,"height":29},"xOffset":0,"yOffset":3,"xAdvance":31}},"kerningDict":{}}}]