{"frames":{"bomb_explosion_00005.png":{"frame":{"x":1,"y":1540,"w":362,"h":365},"rotated":true,"trimmed":true,"spriteSourceSize":{"x":48,"y":33,"w":362,"h":365},"sourceSize":{"w":450,"h":450}},"bomb_explosion_00007.png":{"frame":{"x":1,"y":1169,"w":369,"h":375},"rotated":true,"trimmed":true,"spriteSourceSize":{"x":44,"y":28,"w":369,"h":375},"sourceSize":{"w":450,"h":450}},"bomb_explosion_00008.png":{"frame":{"x":1,"y":793,"w":374,"h":379},"rotated":true,"trimmed":true,"spriteSourceSize":{"x":41,"y":26,"w":374,"h":379},"sourceSize":{"w":450,"h":450}},"bomb_explosion_00010.png":{"frame":{"x":1,"y":407,"w":384,"h":384},"rotated":false,"trimmed":true,"spriteSourceSize":{"x":35,"y":23,"w":384,"h":384},"sourceSize":{"w":450,"h":450}},"bomb_explosion_00013.png":{"frame":{"x":1,"y":1,"w":395,"h":404},"rotated":false,"trimmed":true,"spriteSourceSize":{"x":31,"y":13,"w":395,"h":404},"sourceSize":{"w":450,"h":450}}},"meta":{"app":"http://www.codeandweb.com/texturepacker","version":"1.0","image":"atlas1-xhdpi.png","format":"RGBA8888","size":{"w":397,"h":1903},"scale":"1","smartupdate":"$TexturePacker:SmartUpdate:d9012ec617aa1f7eace1046f75087e14:6deaff0571aa741f7f7aa850b7b4e85e:1d6eadcbdacac7fbac80e6c7c21f4d35$"}}