{"frames":{"bomb_explosion_00000.png":{"frame":{"x":309,"y":1715,"w":190,"h":190},"rotated":false,"trimmed":true,"spriteSourceSize":{"x":133,"y":125,"w":190,"h":190},"sourceSize":{"w":450,"h":450}},"bomb_explosion_00001.png":{"frame":{"x":1,"y":1715,"w":306,"h":308},"rotated":false,"trimmed":true,"spriteSourceSize":{"x":75,"y":65,"w":306,"h":308},"sourceSize":{"w":450,"h":450}},"bomb_explosion_00002.png":{"frame":{"x":1692,"y":1,"w":337,"h":338},"rotated":true,"trimmed":true,"spriteSourceSize":{"x":60,"y":49,"w":337,"h":338},"sourceSize":{"w":450,"h":450}},"bomb_explosion_00003.png":{"frame":{"x":1173,"y":451,"w":347,"h":348},"rotated":false,"trimmed":true,"spriteSourceSize":{"x":55,"y":43,"w":347,"h":348},"sourceSize":{"w":450,"h":450}},"bomb_explosion_00004.png":{"frame":{"x":811,"y":451,"w":355,"h":360},"rotated":true,"trimmed":true,"spriteSourceSize":{"x":52,"y":36,"w":355,"h":360},"sourceSize":{"w":450,"h":450}},"bomb_explosion_00006.png":{"frame":{"x":1676,"y":1656,"w":366,"h":371},"rotated":false,"trimmed":true,"spriteSourceSize":{"x":46,"y":30,"w":366,"h":371},"sourceSize":{"w":450,"h":450}},"bomb_explosion_00009.png":{"frame":{"x":1312,"y":1273,"w":380,"h":381},"rotated":false,"trimmed":true,"spriteSourceSize":{"x":37,"y":25,"w":380,"h":381},"sourceSize":{"w":450,"h":450}},"bomb_explosion_00011.png":{"frame":{"x":1287,"y":1656,"w":389,"h":387},"rotated":true,"trimmed":true,"spriteSourceSize":{"x":34,"y":22,"w":389,"h":387},"sourceSize":{"w":450,"h":450}},"bomb_explosion_00012.png":{"frame":{"x":893,"y":1656,"w":392,"h":389},"rotated":false,"trimmed":true,"spriteSourceSize":{"x":32,"y":20,"w":392,"h":389},"sourceSize":{"w":450,"h":450}},"bomb_explosion_00014.png":{"frame":{"x":893,"y":1255,"w":399,"h":417},"rotated":true,"trimmed":true,"spriteSourceSize":{"x":29,"y":7,"w":399,"h":417},"sourceSize":{"w":450,"h":450}},"bomb_explosion_00015.png":{"frame":{"x":1337,"y":864,"w":407,"h":427},"rotated":true,"trimmed":true,"spriteSourceSize":{"x":25,"y":2,"w":407,"h":427},"sourceSize":{"w":450,"h":450}},"bomb_explosion_00016.png":{"frame":{"x":1522,"y":442,"w":420,"h":433},"rotated":true,"trimmed":true,"spriteSourceSize":{"x":18,"y":0,"w":420,"h":433},"sourceSize":{"w":450,"h":450}},"bomb_explosion_00017.png":{"frame":{"x":1258,"y":1,"w":432,"h":439},"rotated":false,"trimmed":true,"spriteSourceSize":{"x":13,"y":0,"w":432,"h":439},"sourceSize":{"w":450,"h":450}},"bomb_explosion_00018.png":{"frame":{"x":892,"y":808,"w":443,"h":445},"rotated":false,"trimmed":true,"spriteSourceSize":{"x":7,"y":0,"w":443,"h":445},"sourceSize":{"w":450,"h":450}},"bomb_explosion_00019.png":{"frame":{"x":811,"y":1,"w":445,"h":448},"rotated":false,"trimmed":true,"spriteSourceSize":{"x":5,"y":0,"w":445,"h":448},"sourceSize":{"w":450,"h":450}},"bomb_explosion_00020.png":{"frame":{"x":1,"y":1263,"w":444,"h":450},"rotated":false,"trimmed":true,"spriteSourceSize":{"x":6,"y":0,"w":444,"h":450},"sourceSize":{"w":450,"h":450}},"bomb_explosion_00021.png":{"frame":{"x":1,"y":811,"w":445,"h":450},"rotated":false,"trimmed":true,"spriteSourceSize":{"x":5,"y":0,"w":445,"h":450},"sourceSize":{"w":450,"h":450}},"bomb_explosion_00022.png":{"frame":{"x":448,"y":811,"w":442,"h":450},"rotated":false,"trimmed":true,"spriteSourceSize":{"x":8,"y":0,"w":442,"h":450},"sourceSize":{"w":450,"h":450}},"bomb_explosion_00023.png":{"frame":{"x":447,"y":1263,"w":444,"h":450},"rotated":false,"trimmed":true,"spriteSourceSize":{"x":6,"y":0,"w":444,"h":450},"sourceSize":{"w":450,"h":450}},"Bomb_Shockwave_v2.png":{"frame":{"x":1,"y":1,"w":808,"h":808},"rotated":false,"trimmed":false,"spriteSourceSize":{"x":0,"y":0,"w":808,"h":808},"sourceSize":{"w":808,"h":808}}},"meta":{"app":"http://www.codeandweb.com/texturepacker","version":"1.0","image":"atlas0-xhdpi.png","format":"RGBA8888","size":{"w":2043,"h":2046},"scale":"1","smartupdate":"$TexturePacker:SmartUpdate:d9012ec617aa1f7eace1046f75087e14:6deaff0571aa741f7f7aa850b7b4e85e:1d6eadcbdacac7fbac80e6c7c21f4d35$"}}